lpp_solver
