Metadata-Version: 1.1
Name: cmdline-lpp-solver
Version: 0.0.3
Summary: Python command line application with solves linear programming problems.
Home-page: https://github.com/Mtrqq/LPPSolver/blob/master/lpp_solver/__init__.py
Author: Maxym Fuhol, Evgenii Babin
Author-email: maxym.fugol@gmail.com, prototy791@gmail.com
License: MIT
Download-URL: https://github.com/Mtrqq/LPPSolver/archive/0.0.3.tar.gz
Keywords: LINEAR PROGRAMMING,CMD,UTILITY
Platform: UNKNOWN
Classifier: Development Status :: 3 - Alpha
Classifier: License :: OSI Approved :: MIT License
Classifier: Programming Language :: Python :: 3
Classifier: Programming Language :: Python :: 3.4
Classifier: Programming Language :: Python :: 3.5
Classifier: Programming Language :: Python :: 3.6
